app/vulnerable_image_check
