Metadata-Version: 1.1
Name: vulnerable-image-check
Version: 1.0
Summary: Detect vulnerable images in Halo monitored registries.
Home-page: https://github.com/cloudpassage-community/vulnerable_image_check
Author: CloudPassage
Author-email: toolbox@cloudpassage.com
License: BSD
Keywords: cloudpassage halo container security docker containers images cicd api sdk
Platform: UNKNOWN
Classifier: Development Status :: 4 - Beta
Classifier: Intended Audience :: Developers
Classifier: Operating System :: MacOS :: MacOS X
Classifier: Operating System :: POSIX :: Linux
Classifier: Programming Language :: Python :: 2.7
Classifier: Topic :: Security
Classifier: License :: OSI Approved :: BSD License
